[ {
  "nome" : "Grêmio",
  "rodadasJogadas" : 9,
  "pontuacao" : 19,
  "vitorias" : 6,
  "empates" : 1,
  "derrotas" : 1,
  "golsMarcados" : 20,
  "golsSofridos" : 12
}, {
  "nome" : "Fluminense",
  "rodadasJogadas" : 9,
  "pontuacao" : 4,
  "vitorias" : 1,
  "empates" : 1,
  "derrotas" : 6,
  "golsMarcados" : 9,
  "golsSofridos" : 15
}, {
  "nome" : "Atlético MG",
  "rodadasJogadas" : 9,
  "pontuacao" : 9,
  "vitorias" : 3,
  "empates" : 0,
  "derrotas" : 5,
  "golsMarcados" : 16,
  "golsSofridos" : 20
}, {
  "nome" : "São Paulo",
  "rodadasJogadas" : 9,
  "pontuacao" : 12,
  "vitorias" : 4,
  "empates" : 0,
  "derrotas" : 4,
  "golsMarcados" : 12,
  "golsSofridos" : 12
}, {
  "nome" : "Palmeiras",
  "rodadasJogadas" : 9,
  "pontuacao" : 22,
  "vitorias" : 7,
  "empates" : 1,
  "derrotas" : 0,
  "golsMarcados" : 21,
  "golsSofridos" : 8
}, {
  "nome" : "Coritiba",
  "rodadasJogadas" : 9,
  "pontuacao" : 6,
  "vitorias" : 1,
  "empates" : 3,
  "derrotas" : 4,
  "golsMarcados" : 14,
  "golsSofridos" : 20
}, {
  "nome" : "Bragantino",
  "rodadasJogadas" : 9,
  "pontuacao" : 11,
  "vitorias" : 3,
  "empates" : 2,
  "derrotas" : 3,
  "golsMarcados" : 17,
  "golsSofridos" : 18
}, {
  "nome" : "Botafogo",
  "rodadasJogadas" : 9,
  "pontuacao" : 13,
  "vitorias" : 4,
  "empates" : 1,
  "derrotas" : 3,
  "golsMarcados" : 16,
  "golsSofridos" : 17
}, {
  "nome" : "Juventude",
  "rodadasJogadas" : 9,
  "pontuacao" : 5,
  "vitorias" : 1,
  "empates" : 2,
  "derrotas" : 5,
  "golsMarcados" : 14,
  "golsSofridos" : 21
}, {
  "nome" : "Brasil de Pelotas",
  "rodadasJogadas" : 9,
  "pontuacao" : 13,
  "vitorias" : 4,
  "empates" : 1,
  "derrotas" : 3,
  "golsMarcados" : 19,
  "golsSofridos" : 15
} ]